{"asctime": "2025-10-08 19:26:35,231", "name": "ClientTaskWorker", "fullName": "__main__.ClientTaskWorker", "levelname": "INFO", "fl_ctx": "", "message": "ClientTaskWorker started to run"}
{"asctime": "2025-10-08 19:26:35,346", "name": "CoreCell", "fullName": "nvflare.fuel.f3.cellnet.core_cell.CoreCell", "levelname": "INFO", "fl_ctx": "", "message": "site-2.simulate_job: created backbone external connector to tcp://localhost:54047"}
{"asctime": "2025-10-08 19:26:35,346", "name": "conn_manager", "fullName": "nvflare.fuel.f3.sfm.conn_manager", "levelname": "INFO", "fl_ctx": "", "message": "Connector [CH00001 ACTIVE tcp://localhost:54047] is starting"}
{"asctime": "2025-10-08 19:26:35,347", "name": "Cell", "fullName": "nvflare.fuel.f3.cellnet.cell.Cell", "levelname": "INFO", "fl_ctx": "", "message": "Register blob CB for channel='server_command', topic='get_task'"}
{"asctime": "2025-10-08 19:26:35,347", "name": "conn_manager", "fullName": "nvflare.fuel.f3.sfm.conn_manager", "levelname": "INFO", "fl_ctx": "", "message": "Connection [CN00002 127.0.0.1:50458 => 127.0.0.1:54047] is created: PID: 301531"}
{"asctime": "2025-10-08 19:26:35,348", "name": "Cell", "fullName": "nvflare.fuel.f3.cellnet.cell.Cell", "levelname": "INFO", "fl_ctx": "", "message": "Register blob CB for channel='server_command', topic='submit_update'"}
{"asctime": "2025-10-08 19:26:35,448", "name": "AuxRunner", "fullName": "nvflare.private.aux_runner.AuxRunner", "levelname": "INFO", "fl_ctx": "", "message": "registered aux handler for topic ObjectStreamer.Request"}
{"asctime": "2025-10-08 19:26:35,449", "name": "AuxRunner", "fullName": "nvflare.private.aux_runner.AuxRunner", "levelname": "INFO", "fl_ctx": "", "message": "registered aux handler for topic ObjectStreamer.Abort"}
{"asctime": "2025-10-08 19:26:36,365", "name": "AuxRunner", "fullName": "nvflare.private.aux_runner.AuxRunner", "levelname": "INFO", "fl_ctx": "", "message": "registered aux handler for topic ObjectStreamer.Request"}
{"asctime": "2025-10-08 19:26:36,365", "name": "AuxRunner", "fullName": "nvflare.private.aux_runner.AuxRunner", "levelname": "INFO", "fl_ctx": "", "message": "registered aux handler for topic ObjectStreamer.Abort"}
{"asctime": "2025-10-08 19:26:36,366", "name": "AuxRunner", "fullName": "nvflare.private.aux_runner.AuxRunner", "levelname": "INFO", "fl_ctx": "", "message": "registered aux handler for topic __end_run__"}
{"asctime": "2025-10-08 19:26:36,366", "name": "AuxRunner", "fullName": "nvflare.private.aux_runner.AuxRunner", "levelname": "INFO", "fl_ctx": "", "message": "registered aux handler for topic __do_task__"}
{"asctime": "2025-10-08 19:26:36,366", "name": "Cell", "fullName": "nvflare.fuel.f3.cellnet.cell.Cell", "levelname": "INFO", "fl_ctx": "", "message": "Register blob CB for channel='aux_communication', topic='*'"}
{"asctime": "2025-10-08 19:26:36,366", "name": "AuxRunner", "fullName": "nvflare.private.aux_runner.AuxRunner", "levelname": "INFO", "fl_ctx": "", "message": "registered aux handler for topic __sync_runner__"}
{"asctime": "2025-10-08 19:26:36,367", "name": "AuxRunner", "fullName": "nvflare.private.aux_runner.AuxRunner", "levelname": "INFO", "fl_ctx": "", "message": "registered aux handler for topic __job_heartbeat__"}
{"asctime": "2025-10-08 19:26:36,367", "name": "AuxRunner", "fullName": "nvflare.private.aux_runner.AuxRunner", "levelname": "INFO", "fl_ctx": "", "message": "registered aux handler for topic __task_check__"}
{"asctime": "2025-10-08 19:26:36,867", "name": "ClientRunner", "fullName": "nvflare.private.fed.client.client_runner.ClientRunner", "levelname": "INFO", "fl_ctx": "[identity=site-2, run=simulate_job]", "message": "syncing to parent server ..."}
{"asctime": "2025-10-08 19:26:36,875", "name": "ClientRunner", "fullName": "nvflare.private.fed.client.client_runner.ClientRunner", "levelname": "INFO", "fl_ctx": "[identity=site-2, run=simulate_job]", "message": "synced to parent server in 0.508364200592041 seconds"}
{"asctime": "2025-10-08 19:26:36,876", "name": "AuxRunner", "fullName": "nvflare.private.aux_runner.AuxRunner", "levelname": "INFO", "fl_ctx": "", "message": "registered aux handler for topic RM.RELIABLE_REQUEST"}
{"asctime": "2025-10-08 19:26:36,876", "name": "AuxRunner", "fullName": "nvflare.private.aux_runner.AuxRunner", "levelname": "INFO", "fl_ctx": "", "message": "registered aux handler for topic RM.RELIABLE_REPLY"}
{"asctime": "2025-10-08 19:26:36,876", "name": "ReliableMessage", "fullName": "nvflare.apis.utils.reliable_message.ReliableMessage", "levelname": "INFO", "fl_ctx": "", "message": "enabled reliable message: max_request_workers=20 query_interval=2.0"}
{"asctime": "2025-10-08 19:26:36,877", "name": "AuxRunner", "fullName": "nvflare.private.aux_runner.AuxRunner", "levelname": "INFO", "fl_ctx": "", "message": "registered aux handler for topic fed.event"}
{"asctime": "2025-10-08 19:26:36,877", "name": "TaskScriptRunner", "fullName": "nvflare.app_common.executors.task_script_runner.TaskScriptRunner", "levelname": "INFO", "fl_ctx": "", "message": "start task run() with full path: /home/marcelohaps/NVFlare-ResIA/workspace/hello-pt/site-2/simulate_job/app_site-2/custom/client.py"}
{"asctime": "2025-10-08 19:26:36,877", "name": "ClientRunner", "fullName": "nvflare.private.fed.client.client_runner.ClientRunner", "levelname": "INFO", "fl_ctx": "[identity=site-2, run=simulate_job]", "message": "client runner started"}
{"asctime": "2025-10-08 19:26:36,878", "name": "ClientTaskWorker", "fullName": "__main__.ClientTaskWorker", "levelname": "INFO", "fl_ctx": "", "message": "Initialize ClientRunner for client: site-2"}
{"asctime": "2025-10-08 19:26:36,929", "name": "Communicator", "fullName": "nvflare.private.fed.client.communicator.Communicator", "levelname": "INFO", "fl_ctx": "", "message": "Received from server. getTask: train size: 251.9KB (251855 Bytes) time: 0.050828 seconds"}
{"asctime": "2025-10-08 19:26:36,930", "name": "FederatedClient", "fullName": "nvflare.private.fed.client.fed_client.FederatedClient", "levelname": "INFO", "fl_ctx": "", "message": "pull_task completed. Task name:train Status:True "}
{"asctime": "2025-10-08 19:26:36,930", "name": "ClientRunner", "fullName": "nvflare.private.fed.client.client_runner.ClientRunner", "levelname": "INFO", "fl_ctx": "[identity=site-2, run=simulate_job, peer=simulator_server, peer_run=simulate_job]", "message": "got task assignment: name=train, id=366a048c-99fb-4048-9eb9-5dc441de030b"}
{"asctime": "2025-10-08 19:26:36,931", "name": "ClientRunner", "fullName": "nvflare.private.fed.client.client_runner.ClientRunner", "levelname": "INFO", "fl_ctx": "[identity=site-2, run=simulate_job, peer=simulator_server, peer_run=simulate_job, task_name=train, task_id=366a048c-99fb-4048-9eb9-5dc441de030b]", "message": "invoking task executor PTInProcessClientAPIExecutor"}
{"asctime": "2025-10-08 19:26:36,932", "name": "PTInProcessClientAPIExecutor", "fullName": "nvflare.app_opt.pt.in_process_client_api_executor.PTInProcessClientAPIExecutor", "levelname": "INFO", "fl_ctx": "[identity=site-2, run=simulate_job, peer=simulator_server, peer_run=simulate_job, task_name=train, task_id=366a048c-99fb-4048-9eb9-5dc441de030b]", "message": "execute for task (train)"}
{"asctime": "2025-10-08 19:26:36,934", "name": "PTInProcessClientAPIExecutor", "fullName": "nvflare.app_opt.pt.in_process_client_api_executor.PTInProcessClientAPIExecutor", "levelname": "INFO", "fl_ctx": "[identity=site-2, run=simulate_job, peer=simulator_server, peer_run=simulate_job, task_name=train, task_id=366a048c-99fb-4048-9eb9-5dc441de030b]", "message": "send data to peer"}
{"asctime": "2025-10-08 19:26:36,934", "name": "PTInProcessClientAPIExecutor", "fullName": "nvflare.app_opt.pt.in_process_client_api_executor.PTInProcessClientAPIExecutor", "levelname": "INFO", "fl_ctx": "[identity=site-2, run=simulate_job, peer=simulator_server, peer_run=simulate_job, task_name=train, task_id=366a048c-99fb-4048-9eb9-5dc441de030b]", "message": "sending payload to peer"}
{"asctime": "2025-10-08 19:26:36,936", "name": "PTInProcessClientAPIExecutor", "fullName": "nvflare.app_opt.pt.in_process_client_api_executor.PTInProcessClientAPIExecutor", "levelname": "INFO", "fl_ctx": "[identity=site-2, run=simulate_job, peer=simulator_server, peer_run=simulate_job, task_name=train, task_id=366a048c-99fb-4048-9eb9-5dc441de030b]", "message": "Waiting for result from peer"}
{"asctime": "2025-10-08 19:26:38,344", "name": "TaskScriptRunner", "fullName": "nvflare.app_common.executors.task_script_runner.TaskScriptRunner", "levelname": "INFO", "fl_ctx": "", "message": "site = site-2, current_round=0"}
{"asctime": "2025-10-08 19:26:39,002", "name": "TaskScriptRunner", "fullName": "nvflare.app_common.executors.task_script_runner.TaskScriptRunner", "levelname": "INFO", "fl_ctx": "", "message": "site=site-2, Epoch: 0/2, Iteration: 0"}
{"asctime": "2025-10-08 19:26:53,214", "name": "TaskScriptRunner", "fullName": "nvflare.app_common.executors.task_script_runner.TaskScriptRunner", "levelname": "INFO", "fl_ctx": "", "message": "site=site-2, Epoch: 0/2, Iteration: 3000"}
{"asctime": "2025-10-08 19:26:53,813", "name": "TaskScriptRunner", "fullName": "nvflare.app_common.executors.task_script_runner.TaskScriptRunner", "levelname": "INFO", "fl_ctx": "", "message": "site=site-2, Epoch: 0/2, Average Loss: 1.6465402841567993"}
{"asctime": "2025-10-08 19:26:53,820", "name": "TaskScriptRunner", "fullName": "nvflare.app_common.executors.task_script_runner.TaskScriptRunner", "levelname": "INFO", "fl_ctx": "", "message": "site=site-2, Epoch: 1/2, Iteration: 0"}
{"asctime": "2025-10-08 19:27:08,154", "name": "TaskScriptRunner", "fullName": "nvflare.app_common.executors.task_script_runner.TaskScriptRunner", "levelname": "INFO", "fl_ctx": "", "message": "site=site-2, Epoch: 1/2, Iteration: 3000"}
{"asctime": "2025-10-08 19:27:08,787", "name": "TaskScriptRunner", "fullName": "nvflare.app_common.executors.task_script_runner.TaskScriptRunner", "levelname": "INFO", "fl_ctx": "", "message": "site=site-2, Epoch: 1/2, Average Loss: 1.362847924232483"}
{"asctime": "2025-10-08 19:27:08,789", "name": "TaskScriptRunner", "fullName": "nvflare.app_common.executors.task_script_runner.TaskScriptRunner", "levelname": "INFO", "fl_ctx": "", "message": "site=site-2, Round 0, Average Loss: 1.5046941041946411"}
{"asctime": "2025-10-08 19:27:08,790", "name": "TaskScriptRunner", "fullName": "nvflare.app_common.executors.task_script_runner.TaskScriptRunner", "levelname": "INFO", "fl_ctx": "", "message": "Finished Training for site-2"}
{"asctime": "2025-10-08 19:27:08,795", "name": "TaskScriptRunner", "fullName": "nvflare.app_common.executors.task_script_runner.TaskScriptRunner", "levelname": "INFO", "fl_ctx": "", "message": "site: site-2, sending model to server."}
{"asctime": "2025-10-08 19:27:08,795", "name": "InProcessClientAPI", "fullName": "nvflare.client.in_process.api.InProcessClientAPI", "levelname": "INFO", "fl_ctx": "", "message": "Try to send local model back to peer "}
{"asctime": "2025-10-08 19:27:09,036", "name": "ClientRunner", "fullName": "nvflare.private.fed.client.client_runner.ClientRunner", "levelname": "INFO", "fl_ctx": "[identity=site-2, run=simulate_job, peer=simulator_server, peer_run=simulate_job, task_name=train, task_id=366a048c-99fb-4048-9eb9-5dc441de030b]", "message": "finished processing task"}
{"asctime": "2025-10-08 19:27:09,070", "name": "ClientRunner", "fullName": "nvflare.private.fed.client.client_runner.ClientRunner", "levelname": "INFO", "fl_ctx": "[identity=site-2, run=simulate_job, peer=simulator_server, peer_run=simulate_job, task_name=train, task_id=366a048c-99fb-4048-9eb9-5dc441de030b]", "message": "start to send task result to server"}
{"asctime": "2025-10-08 19:27:09,070", "name": "FederatedClient", "fullName": "nvflare.private.fed.client.fed_client.FederatedClient", "levelname": "INFO", "fl_ctx": "", "message": "Starting to push execute result."}
{"asctime": "2025-10-08 19:27:09,125", "name": "Communicator", "fullName": "nvflare.private.fed.client.communicator.Communicator", "levelname": "INFO", "fl_ctx": "", "message": "SubmitUpdate to: server. size: 251.9KB (251885 Bytes). time: 0.054714 seconds"}
{"asctime": "2025-10-08 19:27:09,125", "name": "ClientRunner", "fullName": "nvflare.private.fed.client.client_runner.ClientRunner", "levelname": "INFO", "fl_ctx": "[identity=site-2, run=simulate_job, peer=simulator_server, peer_run=simulate_job, task_name=train, task_id=366a048c-99fb-4048-9eb9-5dc441de030b]", "message": "task result sent to server"}
{"asctime": "2025-10-08 19:27:09,125", "name": "ClientTaskWorker", "fullName": "__main__.ClientTaskWorker", "levelname": "INFO", "fl_ctx": "", "message": "Finished one task run for client: site-2 interval: 2 task_processed: True"}
{"asctime": "2025-10-08 19:27:11,178", "name": "Communicator", "fullName": "nvflare.private.fed.client.communicator.Communicator", "levelname": "INFO", "fl_ctx": "", "message": "Received from server. getTask: train size: 251.9KB (251855 Bytes) time: 0.004830 seconds"}
{"asctime": "2025-10-08 19:27:11,179", "name": "FederatedClient", "fullName": "nvflare.private.fed.client.fed_client.FederatedClient", "levelname": "INFO", "fl_ctx": "", "message": "pull_task completed. Task name:train Status:True "}
{"asctime": "2025-10-08 19:27:11,179", "name": "ClientRunner", "fullName": "nvflare.private.fed.client.client_runner.ClientRunner", "levelname": "INFO", "fl_ctx": "[identity=site-2, run=simulate_job, peer=simulator_server, peer_run=simulate_job]", "message": "got task assignment: name=train, id=2c0d9446-68b5-4572-84d6-c518821cad7e"}
{"asctime": "2025-10-08 19:27:11,179", "name": "ClientRunner", "fullName": "nvflare.private.fed.client.client_runner.ClientRunner", "levelname": "INFO", "fl_ctx": "[identity=site-2, run=simulate_job, peer=simulator_server, peer_run=simulate_job, task_name=train, task_id=2c0d9446-68b5-4572-84d6-c518821cad7e]", "message": "invoking task executor PTInProcessClientAPIExecutor"}
{"asctime": "2025-10-08 19:27:11,179", "name": "PTInProcessClientAPIExecutor", "fullName": "nvflare.app_opt.pt.in_process_client_api_executor.PTInProcessClientAPIExecutor", "levelname": "INFO", "fl_ctx": "[identity=site-2, run=simulate_job, peer=simulator_server, peer_run=simulate_job, task_name=train, task_id=2c0d9446-68b5-4572-84d6-c518821cad7e]", "message": "execute for task (train)"}
{"asctime": "2025-10-08 19:27:11,180", "name": "PTInProcessClientAPIExecutor", "fullName": "nvflare.app_opt.pt.in_process_client_api_executor.PTInProcessClientAPIExecutor", "levelname": "INFO", "fl_ctx": "[identity=site-2, run=simulate_job, peer=simulator_server, peer_run=simulate_job, task_name=train, task_id=2c0d9446-68b5-4572-84d6-c518821cad7e]", "message": "send data to peer"}
{"asctime": "2025-10-08 19:27:11,180", "name": "PTInProcessClientAPIExecutor", "fullName": "nvflare.app_opt.pt.in_process_client_api_executor.PTInProcessClientAPIExecutor", "levelname": "INFO", "fl_ctx": "[identity=site-2, run=simulate_job, peer=simulator_server, peer_run=simulate_job, task_name=train, task_id=2c0d9446-68b5-4572-84d6-c518821cad7e]", "message": "sending payload to peer"}
{"asctime": "2025-10-08 19:27:11,181", "name": "PTInProcessClientAPIExecutor", "fullName": "nvflare.app_opt.pt.in_process_client_api_executor.PTInProcessClientAPIExecutor", "levelname": "INFO", "fl_ctx": "[identity=site-2, run=simulate_job, peer=simulator_server, peer_run=simulate_job, task_name=train, task_id=2c0d9446-68b5-4572-84d6-c518821cad7e]", "message": "Waiting for result from peer"}
{"asctime": "2025-10-08 19:27:11,297", "name": "TaskScriptRunner", "fullName": "nvflare.app_common.executors.task_script_runner.TaskScriptRunner", "levelname": "INFO", "fl_ctx": "", "message": "site = site-2, current_round=1"}
{"asctime": "2025-10-08 19:27:11,310", "name": "TaskScriptRunner", "fullName": "nvflare.app_common.executors.task_script_runner.TaskScriptRunner", "levelname": "INFO", "fl_ctx": "", "message": "site=site-2, Epoch: 0/2, Iteration: 0"}
{"asctime": "2025-10-08 19:27:25,212", "name": "TaskScriptRunner", "fullName": "nvflare.app_common.executors.task_script_runner.TaskScriptRunner", "levelname": "INFO", "fl_ctx": "", "message": "site=site-2, Epoch: 0/2, Iteration: 3000"}
{"asctime": "2025-10-08 19:27:25,834", "name": "TaskScriptRunner", "fullName": "nvflare.app_common.executors.task_script_runner.TaskScriptRunner", "levelname": "INFO", "fl_ctx": "", "message": "site=site-2, Epoch: 0/2, Average Loss: 1.2996567487716675"}
{"asctime": "2025-10-08 19:27:25,840", "name": "TaskScriptRunner", "fullName": "nvflare.app_common.executors.task_script_runner.TaskScriptRunner", "levelname": "INFO", "fl_ctx": "", "message": "site=site-2, Epoch: 1/2, Iteration: 0"}
{"asctime": "2025-10-08 19:27:40,238", "name": "TaskScriptRunner", "fullName": "nvflare.app_common.executors.task_script_runner.TaskScriptRunner", "levelname": "INFO", "fl_ctx": "", "message": "site=site-2, Epoch: 1/2, Iteration: 3000"}
{"asctime": "2025-10-08 19:27:40,766", "name": "TaskScriptRunner", "fullName": "nvflare.app_common.executors.task_script_runner.TaskScriptRunner", "levelname": "INFO", "fl_ctx": "", "message": "site=site-2, Epoch: 1/2, Average Loss: 1.2286473512649536"}
{"asctime": "2025-10-08 19:27:40,768", "name": "TaskScriptRunner", "fullName": "nvflare.app_common.executors.task_script_runner.TaskScriptRunner", "levelname": "INFO", "fl_ctx": "", "message": "site=site-2, Round 1, Average Loss: 1.2641520500183105"}
{"asctime": "2025-10-08 19:27:40,769", "name": "TaskScriptRunner", "fullName": "nvflare.app_common.executors.task_script_runner.TaskScriptRunner", "levelname": "INFO", "fl_ctx": "", "message": "Finished Training for site-2"}
{"asctime": "2025-10-08 19:27:40,773", "name": "TaskScriptRunner", "fullName": "nvflare.app_common.executors.task_script_runner.TaskScriptRunner", "levelname": "INFO", "fl_ctx": "", "message": "site: site-2, sending model to server."}
{"asctime": "2025-10-08 19:27:40,773", "name": "InProcessClientAPI", "fullName": "nvflare.client.in_process.api.InProcessClientAPI", "levelname": "INFO", "fl_ctx": "", "message": "Try to send local model back to peer "}
{"asctime": "2025-10-08 19:27:40,817", "name": "ClientRunner", "fullName": "nvflare.private.fed.client.client_runner.ClientRunner", "levelname": "INFO", "fl_ctx": "[identity=site-2, run=simulate_job, peer=simulator_server, peer_run=simulate_job, task_name=train, task_id=2c0d9446-68b5-4572-84d6-c518821cad7e]", "message": "finished processing task"}
{"asctime": "2025-10-08 19:27:40,821", "name": "ClientRunner", "fullName": "nvflare.private.fed.client.client_runner.ClientRunner", "levelname": "INFO", "fl_ctx": "[identity=site-2, run=simulate_job, peer=simulator_server, peer_run=simulate_job, task_name=train, task_id=2c0d9446-68b5-4572-84d6-c518821cad7e]", "message": "start to send task result to server"}
{"asctime": "2025-10-08 19:27:40,821", "name": "FederatedClient", "fullName": "nvflare.private.fed.client.fed_client.FederatedClient", "levelname": "INFO", "fl_ctx": "", "message": "Starting to push execute result."}
{"asctime": "2025-10-08 19:27:40,875", "name": "Communicator", "fullName": "nvflare.private.fed.client.communicator.Communicator", "levelname": "INFO", "fl_ctx": "", "message": "SubmitUpdate to: server. size: 251.9KB (251885 Bytes). time: 0.054019 seconds"}
{"asctime": "2025-10-08 19:27:40,875", "name": "ClientRunner", "fullName": "nvflare.private.fed.client.client_runner.ClientRunner", "levelname": "INFO", "fl_ctx": "[identity=site-2, run=simulate_job, peer=simulator_server, peer_run=simulate_job, task_name=train, task_id=2c0d9446-68b5-4572-84d6-c518821cad7e]", "message": "task result sent to server"}
{"asctime": "2025-10-08 19:27:40,876", "name": "ClientTaskWorker", "fullName": "__main__.ClientTaskWorker", "levelname": "INFO", "fl_ctx": "", "message": "Finished one task run for client: site-2 interval: 2 task_processed: True"}
{"asctime": "2025-10-08 19:27:42,883", "name": "Communicator", "fullName": "nvflare.private.fed.client.communicator.Communicator", "levelname": "INFO", "fl_ctx": "", "message": "Received from server. getTask: train size: 251.9KB (251855 Bytes) time: 0.004526 seconds"}
{"asctime": "2025-10-08 19:27:42,883", "name": "FederatedClient", "fullName": "nvflare.private.fed.client.fed_client.FederatedClient", "levelname": "INFO", "fl_ctx": "", "message": "pull_task completed. Task name:train Status:True "}
{"asctime": "2025-10-08 19:27:42,883", "name": "ClientRunner", "fullName": "nvflare.private.fed.client.client_runner.ClientRunner", "levelname": "INFO", "fl_ctx": "[identity=site-2, run=simulate_job, peer=simulator_server, peer_run=simulate_job]", "message": "got task assignment: name=train, id=12bb3525-8e31-40cd-afc0-39fdadfb9572"}
{"asctime": "2025-10-08 19:27:42,884", "name": "ClientRunner", "fullName": "nvflare.private.fed.client.client_runner.ClientRunner", "levelname": "INFO", "fl_ctx": "[identity=site-2, run=simulate_job, peer=simulator_server, peer_run=simulate_job, task_name=train, task_id=12bb3525-8e31-40cd-afc0-39fdadfb9572]", "message": "invoking task executor PTInProcessClientAPIExecutor"}
{"asctime": "2025-10-08 19:27:42,884", "name": "PTInProcessClientAPIExecutor", "fullName": "nvflare.app_opt.pt.in_process_client_api_executor.PTInProcessClientAPIExecutor", "levelname": "INFO", "fl_ctx": "[identity=site-2, run=simulate_job, peer=simulator_server, peer_run=simulate_job, task_name=train, task_id=12bb3525-8e31-40cd-afc0-39fdadfb9572]", "message": "execute for task (train)"}
{"asctime": "2025-10-08 19:27:42,884", "name": "PTInProcessClientAPIExecutor", "fullName": "nvflare.app_opt.pt.in_process_client_api_executor.PTInProcessClientAPIExecutor", "levelname": "INFO", "fl_ctx": "[identity=site-2, run=simulate_job, peer=simulator_server, peer_run=simulate_job, task_name=train, task_id=12bb3525-8e31-40cd-afc0-39fdadfb9572]", "message": "send data to peer"}
{"asctime": "2025-10-08 19:27:42,885", "name": "PTInProcessClientAPIExecutor", "fullName": "nvflare.app_opt.pt.in_process_client_api_executor.PTInProcessClientAPIExecutor", "levelname": "INFO", "fl_ctx": "[identity=site-2, run=simulate_job, peer=simulator_server, peer_run=simulate_job, task_name=train, task_id=12bb3525-8e31-40cd-afc0-39fdadfb9572]", "message": "sending payload to peer"}
{"asctime": "2025-10-08 19:27:42,885", "name": "PTInProcessClientAPIExecutor", "fullName": "nvflare.app_opt.pt.in_process_client_api_executor.PTInProcessClientAPIExecutor", "levelname": "INFO", "fl_ctx": "[identity=site-2, run=simulate_job, peer=simulator_server, peer_run=simulate_job, task_name=train, task_id=12bb3525-8e31-40cd-afc0-39fdadfb9572]", "message": "Waiting for result from peer"}
{"asctime": "2025-10-08 19:27:43,276", "name": "TaskScriptRunner", "fullName": "nvflare.app_common.executors.task_script_runner.TaskScriptRunner", "levelname": "INFO", "fl_ctx": "", "message": "site = site-2, current_round=2"}
{"asctime": "2025-10-08 19:27:43,288", "name": "TaskScriptRunner", "fullName": "nvflare.app_common.executors.task_script_runner.TaskScriptRunner", "levelname": "INFO", "fl_ctx": "", "message": "site=site-2, Epoch: 0/2, Iteration: 0"}
{"asctime": "2025-10-08 19:27:56,683", "name": "TaskScriptRunner", "fullName": "nvflare.app_common.executors.task_script_runner.TaskScriptRunner", "levelname": "INFO", "fl_ctx": "", "message": "site=site-2, Epoch: 0/2, Iteration: 3000"}
{"asctime": "2025-10-08 19:27:57,300", "name": "TaskScriptRunner", "fullName": "nvflare.app_common.executors.task_script_runner.TaskScriptRunner", "levelname": "INFO", "fl_ctx": "", "message": "site=site-2, Epoch: 0/2, Average Loss: 1.168949842453003"}
{"asctime": "2025-10-08 19:27:57,308", "name": "TaskScriptRunner", "fullName": "nvflare.app_common.executors.task_script_runner.TaskScriptRunner", "levelname": "INFO", "fl_ctx": "", "message": "site=site-2, Epoch: 1/2, Iteration: 0"}
{"asctime": "2025-10-08 19:28:13,417", "name": "TaskScriptRunner", "fullName": "nvflare.app_common.executors.task_script_runner.TaskScriptRunner", "levelname": "INFO", "fl_ctx": "", "message": "site=site-2, Epoch: 1/2, Iteration: 3000"}
{"asctime": "2025-10-08 19:28:13,960", "name": "TaskScriptRunner", "fullName": "nvflare.app_common.executors.task_script_runner.TaskScriptRunner", "levelname": "INFO", "fl_ctx": "", "message": "site=site-2, Epoch: 1/2, Average Loss: 1.1503525972366333"}
{"asctime": "2025-10-08 19:28:13,961", "name": "TaskScriptRunner", "fullName": "nvflare.app_common.executors.task_script_runner.TaskScriptRunner", "levelname": "INFO", "fl_ctx": "", "message": "site=site-2, Round 2, Average Loss: 1.159651279449463"}
{"asctime": "2025-10-08 19:28:13,962", "name": "TaskScriptRunner", "fullName": "nvflare.app_common.executors.task_script_runner.TaskScriptRunner", "levelname": "INFO", "fl_ctx": "", "message": "Finished Training for site-2"}
{"asctime": "2025-10-08 19:28:13,966", "name": "TaskScriptRunner", "fullName": "nvflare.app_common.executors.task_script_runner.TaskScriptRunner", "levelname": "INFO", "fl_ctx": "", "message": "site: site-2, sending model to server."}
{"asctime": "2025-10-08 19:28:13,966", "name": "InProcessClientAPI", "fullName": "nvflare.client.in_process.api.InProcessClientAPI", "levelname": "INFO", "fl_ctx": "", "message": "Try to send local model back to peer "}
{"asctime": "2025-10-08 19:28:14,460", "name": "ClientRunner", "fullName": "nvflare.private.fed.client.client_runner.ClientRunner", "levelname": "INFO", "fl_ctx": "[identity=site-2, run=simulate_job, peer=simulator_server, peer_run=simulate_job, task_name=train, task_id=12bb3525-8e31-40cd-afc0-39fdadfb9572]", "message": "finished processing task"}
{"asctime": "2025-10-08 19:28:14,463", "name": "ClientRunner", "fullName": "nvflare.private.fed.client.client_runner.ClientRunner", "levelname": "INFO", "fl_ctx": "[identity=site-2, run=simulate_job, peer=simulator_server, peer_run=simulate_job, task_name=train, task_id=12bb3525-8e31-40cd-afc0-39fdadfb9572]", "message": "start to send task result to server"}
{"asctime": "2025-10-08 19:28:14,463", "name": "FederatedClient", "fullName": "nvflare.private.fed.client.fed_client.FederatedClient", "levelname": "INFO", "fl_ctx": "", "message": "Starting to push execute result."}
{"asctime": "2025-10-08 19:28:14,519", "name": "Communicator", "fullName": "nvflare.private.fed.client.communicator.Communicator", "levelname": "INFO", "fl_ctx": "", "message": "SubmitUpdate to: server. size: 251.9KB (251885 Bytes). time: 0.055262 seconds"}
{"asctime": "2025-10-08 19:28:14,519", "name": "ClientRunner", "fullName": "nvflare.private.fed.client.client_runner.ClientRunner", "levelname": "INFO", "fl_ctx": "[identity=site-2, run=simulate_job, peer=simulator_server, peer_run=simulate_job, task_name=train, task_id=12bb3525-8e31-40cd-afc0-39fdadfb9572]", "message": "task result sent to server"}
{"asctime": "2025-10-08 19:28:14,519", "name": "ClientTaskWorker", "fullName": "__main__.ClientTaskWorker", "levelname": "INFO", "fl_ctx": "", "message": "Finished one task run for client: site-2 interval: 2 task_processed: True"}
{"asctime": "2025-10-08 19:28:16,528", "name": "Communicator", "fullName": "nvflare.private.fed.client.communicator.Communicator", "levelname": "INFO", "fl_ctx": "", "message": "Received from server. getTask: train size: 251.9KB (251855 Bytes) time: 0.006653 seconds"}
{"asctime": "2025-10-08 19:28:16,528", "name": "FederatedClient", "fullName": "nvflare.private.fed.client.fed_client.FederatedClient", "levelname": "INFO", "fl_ctx": "", "message": "pull_task completed. Task name:train Status:True "}
{"asctime": "2025-10-08 19:28:16,528", "name": "ClientRunner", "fullName": "nvflare.private.fed.client.client_runner.ClientRunner", "levelname": "INFO", "fl_ctx": "[identity=site-2, run=simulate_job, peer=simulator_server, peer_run=simulate_job]", "message": "got task assignment: name=train, id=da99dd1b-8460-4a36-bb88-63786ceb7ca8"}
{"asctime": "2025-10-08 19:28:16,529", "name": "ClientRunner", "fullName": "nvflare.private.fed.client.client_runner.ClientRunner", "levelname": "INFO", "fl_ctx": "[identity=site-2, run=simulate_job, peer=simulator_server, peer_run=simulate_job, task_name=train, task_id=da99dd1b-8460-4a36-bb88-63786ceb7ca8]", "message": "invoking task executor PTInProcessClientAPIExecutor"}
{"asctime": "2025-10-08 19:28:16,529", "name": "PTInProcessClientAPIExecutor", "fullName": "nvflare.app_opt.pt.in_process_client_api_executor.PTInProcessClientAPIExecutor", "levelname": "INFO", "fl_ctx": "[identity=site-2, run=simulate_job, peer=simulator_server, peer_run=simulate_job, task_name=train, task_id=da99dd1b-8460-4a36-bb88-63786ceb7ca8]", "message": "execute for task (train)"}
{"asctime": "2025-10-08 19:28:16,530", "name": "PTInProcessClientAPIExecutor", "fullName": "nvflare.app_opt.pt.in_process_client_api_executor.PTInProcessClientAPIExecutor", "levelname": "INFO", "fl_ctx": "[identity=site-2, run=simulate_job, peer=simulator_server, peer_run=simulate_job, task_name=train, task_id=da99dd1b-8460-4a36-bb88-63786ceb7ca8]", "message": "send data to peer"}
{"asctime": "2025-10-08 19:28:16,530", "name": "PTInProcessClientAPIExecutor", "fullName": "nvflare.app_opt.pt.in_process_client_api_executor.PTInProcessClientAPIExecutor", "levelname": "INFO", "fl_ctx": "[identity=site-2, run=simulate_job, peer=simulator_server, peer_run=simulate_job, task_name=train, task_id=da99dd1b-8460-4a36-bb88-63786ceb7ca8]", "message": "sending payload to peer"}
{"asctime": "2025-10-08 19:28:16,531", "name": "PTInProcessClientAPIExecutor", "fullName": "nvflare.app_opt.pt.in_process_client_api_executor.PTInProcessClientAPIExecutor", "levelname": "INFO", "fl_ctx": "[identity=site-2, run=simulate_job, peer=simulator_server, peer_run=simulate_job, task_name=train, task_id=da99dd1b-8460-4a36-bb88-63786ceb7ca8]", "message": "Waiting for result from peer"}
{"asctime": "2025-10-08 19:28:16,969", "name": "TaskScriptRunner", "fullName": "nvflare.app_common.executors.task_script_runner.TaskScriptRunner", "levelname": "INFO", "fl_ctx": "", "message": "site = site-2, current_round=3"}
{"asctime": "2025-10-08 19:28:16,984", "name": "TaskScriptRunner", "fullName": "nvflare.app_common.executors.task_script_runner.TaskScriptRunner", "levelname": "INFO", "fl_ctx": "", "message": "site=site-2, Epoch: 0/2, Iteration: 0"}
{"asctime": "2025-10-08 19:28:31,842", "name": "TaskScriptRunner", "fullName": "nvflare.app_common.executors.task_script_runner.TaskScriptRunner", "levelname": "INFO", "fl_ctx": "", "message": "site=site-2, Epoch: 0/2, Iteration: 3000"}
{"asctime": "2025-10-08 19:28:32,440", "name": "TaskScriptRunner", "fullName": "nvflare.app_common.executors.task_script_runner.TaskScriptRunner", "levelname": "INFO", "fl_ctx": "", "message": "site=site-2, Epoch: 0/2, Average Loss: 1.09188973903656"}
{"asctime": "2025-10-08 19:28:32,448", "name": "TaskScriptRunner", "fullName": "nvflare.app_common.executors.task_script_runner.TaskScriptRunner", "levelname": "INFO", "fl_ctx": "", "message": "site=site-2, Epoch: 1/2, Iteration: 0"}
{"asctime": "2025-10-08 19:28:47,755", "name": "TaskScriptRunner", "fullName": "nvflare.app_common.executors.task_script_runner.TaskScriptRunner", "levelname": "INFO", "fl_ctx": "", "message": "site=site-2, Epoch: 1/2, Iteration: 3000"}
{"asctime": "2025-10-08 19:28:48,272", "name": "TaskScriptRunner", "fullName": "nvflare.app_common.executors.task_script_runner.TaskScriptRunner", "levelname": "INFO", "fl_ctx": "", "message": "site=site-2, Epoch: 1/2, Average Loss: 1.0927075147628784"}
{"asctime": "2025-10-08 19:28:48,273", "name": "TaskScriptRunner", "fullName": "nvflare.app_common.executors.task_script_runner.TaskScriptRunner", "levelname": "INFO", "fl_ctx": "", "message": "site=site-2, Round 3, Average Loss: 1.0922986268997192"}
{"asctime": "2025-10-08 19:28:48,274", "name": "TaskScriptRunner", "fullName": "nvflare.app_common.executors.task_script_runner.TaskScriptRunner", "levelname": "INFO", "fl_ctx": "", "message": "Finished Training for site-2"}
{"asctime": "2025-10-08 19:28:48,277", "name": "TaskScriptRunner", "fullName": "nvflare.app_common.executors.task_script_runner.TaskScriptRunner", "levelname": "INFO", "fl_ctx": "", "message": "site: site-2, sending model to server."}
{"asctime": "2025-10-08 19:28:48,278", "name": "InProcessClientAPI", "fullName": "nvflare.client.in_process.api.InProcessClientAPI", "levelname": "INFO", "fl_ctx": "", "message": "Try to send local model back to peer "}
{"asctime": "2025-10-08 19:28:48,681", "name": "ClientRunner", "fullName": "nvflare.private.fed.client.client_runner.ClientRunner", "levelname": "INFO", "fl_ctx": "[identity=site-2, run=simulate_job, peer=simulator_server, peer_run=simulate_job, task_name=train, task_id=da99dd1b-8460-4a36-bb88-63786ceb7ca8]", "message": "finished processing task"}
{"asctime": "2025-10-08 19:28:48,685", "name": "ClientRunner", "fullName": "nvflare.private.fed.client.client_runner.ClientRunner", "levelname": "INFO", "fl_ctx": "[identity=site-2, run=simulate_job, peer=simulator_server, peer_run=simulate_job, task_name=train, task_id=da99dd1b-8460-4a36-bb88-63786ceb7ca8]", "message": "start to send task result to server"}
{"asctime": "2025-10-08 19:28:48,685", "name": "FederatedClient", "fullName": "nvflare.private.fed.client.fed_client.FederatedClient", "levelname": "INFO", "fl_ctx": "", "message": "Starting to push execute result."}
{"asctime": "2025-10-08 19:28:48,743", "name": "Communicator", "fullName": "nvflare.private.fed.client.communicator.Communicator", "levelname": "INFO", "fl_ctx": "", "message": "SubmitUpdate to: server. size: 251.9KB (251885 Bytes). time: 0.058229 seconds"}
{"asctime": "2025-10-08 19:28:48,744", "name": "ClientRunner", "fullName": "nvflare.private.fed.client.client_runner.ClientRunner", "levelname": "INFO", "fl_ctx": "[identity=site-2, run=simulate_job, peer=simulator_server, peer_run=simulate_job, task_name=train, task_id=da99dd1b-8460-4a36-bb88-63786ceb7ca8]", "message": "task result sent to server"}
{"asctime": "2025-10-08 19:28:48,744", "name": "ClientTaskWorker", "fullName": "__main__.ClientTaskWorker", "levelname": "INFO", "fl_ctx": "", "message": "Finished one task run for client: site-2 interval: 2 task_processed: True"}
{"asctime": "2025-10-08 19:28:50,751", "name": "Communicator", "fullName": "nvflare.private.fed.client.communicator.Communicator", "levelname": "INFO", "fl_ctx": "", "message": "Received from server. getTask: train size: 251.9KB (251855 Bytes) time: 0.005620 seconds"}
{"asctime": "2025-10-08 19:28:50,752", "name": "FederatedClient", "fullName": "nvflare.private.fed.client.fed_client.FederatedClient", "levelname": "INFO", "fl_ctx": "", "message": "pull_task completed. Task name:train Status:True "}
{"asctime": "2025-10-08 19:28:50,752", "name": "ClientRunner", "fullName": "nvflare.private.fed.client.client_runner.ClientRunner", "levelname": "INFO", "fl_ctx": "[identity=site-2, run=simulate_job, peer=simulator_server, peer_run=simulate_job]", "message": "got task assignment: name=train, id=bc667a9c-0274-4548-a0d2-7f561540aa1a"}
{"asctime": "2025-10-08 19:28:50,752", "name": "ClientRunner", "fullName": "nvflare.private.fed.client.client_runner.ClientRunner", "levelname": "INFO", "fl_ctx": "[identity=site-2, run=simulate_job, peer=simulator_server, peer_run=simulate_job, task_name=train, task_id=bc667a9c-0274-4548-a0d2-7f561540aa1a]", "message": "invoking task executor PTInProcessClientAPIExecutor"}
{"asctime": "2025-10-08 19:28:50,753", "name": "PTInProcessClientAPIExecutor", "fullName": "nvflare.app_opt.pt.in_process_client_api_executor.PTInProcessClientAPIExecutor", "levelname": "INFO", "fl_ctx": "[identity=site-2, run=simulate_job, peer=simulator_server, peer_run=simulate_job, task_name=train, task_id=bc667a9c-0274-4548-a0d2-7f561540aa1a]", "message": "execute for task (train)"}
{"asctime": "2025-10-08 19:28:50,753", "name": "PTInProcessClientAPIExecutor", "fullName": "nvflare.app_opt.pt.in_process_client_api_executor.PTInProcessClientAPIExecutor", "levelname": "INFO", "fl_ctx": "[identity=site-2, run=simulate_job, peer=simulator_server, peer_run=simulate_job, task_name=train, task_id=bc667a9c-0274-4548-a0d2-7f561540aa1a]", "message": "send data to peer"}
{"asctime": "2025-10-08 19:28:50,754", "name": "PTInProcessClientAPIExecutor", "fullName": "nvflare.app_opt.pt.in_process_client_api_executor.PTInProcessClientAPIExecutor", "levelname": "INFO", "fl_ctx": "[identity=site-2, run=simulate_job, peer=simulator_server, peer_run=simulate_job, task_name=train, task_id=bc667a9c-0274-4548-a0d2-7f561540aa1a]", "message": "sending payload to peer"}
{"asctime": "2025-10-08 19:28:50,754", "name": "PTInProcessClientAPIExecutor", "fullName": "nvflare.app_opt.pt.in_process_client_api_executor.PTInProcessClientAPIExecutor", "levelname": "INFO", "fl_ctx": "[identity=site-2, run=simulate_job, peer=simulator_server, peer_run=simulate_job, task_name=train, task_id=bc667a9c-0274-4548-a0d2-7f561540aa1a]", "message": "Waiting for result from peer"}
{"asctime": "2025-10-08 19:28:50,780", "name": "TaskScriptRunner", "fullName": "nvflare.app_common.executors.task_script_runner.TaskScriptRunner", "levelname": "INFO", "fl_ctx": "", "message": "site = site-2, current_round=4"}
{"asctime": "2025-10-08 19:28:50,793", "name": "TaskScriptRunner", "fullName": "nvflare.app_common.executors.task_script_runner.TaskScriptRunner", "levelname": "INFO", "fl_ctx": "", "message": "site=site-2, Epoch: 0/2, Iteration: 0"}
{"asctime": "2025-10-08 19:29:05,669", "name": "TaskScriptRunner", "fullName": "nvflare.app_common.executors.task_script_runner.TaskScriptRunner", "levelname": "INFO", "fl_ctx": "", "message": "site=site-2, Epoch: 0/2, Iteration: 3000"}
{"asctime": "2025-10-08 19:29:06,277", "name": "TaskScriptRunner", "fullName": "nvflare.app_common.executors.task_script_runner.TaskScriptRunner", "levelname": "INFO", "fl_ctx": "", "message": "site=site-2, Epoch: 0/2, Average Loss: 1.0343399047851562"}
{"asctime": "2025-10-08 19:29:06,287", "name": "TaskScriptRunner", "fullName": "nvflare.app_common.executors.task_script_runner.TaskScriptRunner", "levelname": "INFO", "fl_ctx": "", "message": "site=site-2, Epoch: 1/2, Iteration: 0"}
{"asctime": "2025-10-08 19:29:21,082", "name": "TaskScriptRunner", "fullName": "nvflare.app_common.executors.task_script_runner.TaskScriptRunner", "levelname": "INFO", "fl_ctx": "", "message": "site=site-2, Epoch: 1/2, Iteration: 3000"}
{"asctime": "2025-10-08 19:29:21,561", "name": "TaskScriptRunner", "fullName": "nvflare.app_common.executors.task_script_runner.TaskScriptRunner", "levelname": "INFO", "fl_ctx": "", "message": "site=site-2, Epoch: 1/2, Average Loss: 1.0711596012115479"}
{"asctime": "2025-10-08 19:29:21,563", "name": "TaskScriptRunner", "fullName": "nvflare.app_common.executors.task_script_runner.TaskScriptRunner", "levelname": "INFO", "fl_ctx": "", "message": "site=site-2, Round 4, Average Loss: 1.052749752998352"}
{"asctime": "2025-10-08 19:29:21,563", "name": "TaskScriptRunner", "fullName": "nvflare.app_common.executors.task_script_runner.TaskScriptRunner", "levelname": "INFO", "fl_ctx": "", "message": "Finished Training for site-2"}
{"asctime": "2025-10-08 19:29:21,567", "name": "TaskScriptRunner", "fullName": "nvflare.app_common.executors.task_script_runner.TaskScriptRunner", "levelname": "INFO", "fl_ctx": "", "message": "site: site-2, sending model to server."}
{"asctime": "2025-10-08 19:29:21,567", "name": "InProcessClientAPI", "fullName": "nvflare.client.in_process.api.InProcessClientAPI", "levelname": "INFO", "fl_ctx": "", "message": "Try to send local model back to peer "}
{"asctime": "2025-10-08 19:29:21,860", "name": "ClientRunner", "fullName": "nvflare.private.fed.client.client_runner.ClientRunner", "levelname": "INFO", "fl_ctx": "[identity=site-2, run=simulate_job, peer=simulator_server, peer_run=simulate_job, task_name=train, task_id=bc667a9c-0274-4548-a0d2-7f561540aa1a]", "message": "finished processing task"}
{"asctime": "2025-10-08 19:29:21,863", "name": "ClientRunner", "fullName": "nvflare.private.fed.client.client_runner.ClientRunner", "levelname": "INFO", "fl_ctx": "[identity=site-2, run=simulate_job, peer=simulator_server, peer_run=simulate_job, task_name=train, task_id=bc667a9c-0274-4548-a0d2-7f561540aa1a]", "message": "start to send task result to server"}
{"asctime": "2025-10-08 19:29:21,863", "name": "FederatedClient", "fullName": "nvflare.private.fed.client.fed_client.FederatedClient", "levelname": "INFO", "fl_ctx": "", "message": "Starting to push execute result."}
{"asctime": "2025-10-08 19:29:21,915", "name": "Communicator", "fullName": "nvflare.private.fed.client.communicator.Communicator", "levelname": "INFO", "fl_ctx": "", "message": "SubmitUpdate to: server. size: 251.9KB (251885 Bytes). time: 0.051574 seconds"}
{"asctime": "2025-10-08 19:29:21,916", "name": "ClientRunner", "fullName": "nvflare.private.fed.client.client_runner.ClientRunner", "levelname": "INFO", "fl_ctx": "[identity=site-2, run=simulate_job, peer=simulator_server, peer_run=simulate_job, task_name=train, task_id=bc667a9c-0274-4548-a0d2-7f561540aa1a]", "message": "task result sent to server"}
{"asctime": "2025-10-08 19:29:21,916", "name": "ClientTaskWorker", "fullName": "__main__.ClientTaskWorker", "levelname": "INFO", "fl_ctx": "", "message": "Finished one task run for client: site-2 interval: 2 task_processed: True"}
{"asctime": "2025-10-08 19:29:22,051", "name": "ClientRunner", "fullName": "nvflare.private.fed.client.client_runner.ClientRunner", "levelname": "INFO", "fl_ctx": "[identity=site-2, run=simulate_job, peer=simulator_server, peer_run=simulate_job]", "message": "received request from Server to end current RUN"}
{"asctime": "2025-10-08 19:29:23,920", "name": "FederatedClient", "fullName": "nvflare.private.fed.client.fed_client.FederatedClient", "levelname": "INFO", "fl_ctx": "", "message": "pull_task completed. Task name:__end_run__ Status:True "}
{"asctime": "2025-10-08 19:29:23,920", "name": "ClientRunner", "fullName": "nvflare.private.fed.client.client_runner.ClientRunner", "levelname": "INFO", "fl_ctx": "[identity=site-2, run=simulate_job, peer=simulator_server, peer_run=simulate_job]", "message": "server asked to end the run"}
{"asctime": "2025-10-08 19:29:23,921", "name": "ClientRunner", "fullName": "nvflare.private.fed.client.client_runner.ClientRunner", "levelname": "INFO", "fl_ctx": "[identity=site-2, run=simulate_job]", "message": "started end-run events sequence"}
{"asctime": "2025-10-08 19:29:23,921", "name": "ClientRunner", "fullName": "nvflare.private.fed.client.client_runner.ClientRunner", "levelname": "INFO", "fl_ctx": "[identity=site-2, run=simulate_job]", "message": "ABOUT_TO_END_RUN fired"}
{"asctime": "2025-10-08 19:29:23,921", "name": "ClientRunner", "fullName": "nvflare.private.fed.client.client_runner.ClientRunner", "levelname": "INFO", "fl_ctx": "[identity=site-2, run=simulate_job]", "message": "Firing CHECK_END_RUN_READINESS ..."}
{"asctime": "2025-10-08 19:29:23,922", "name": "InProcessClientAPI", "fullName": "nvflare.client.in_process.api.InProcessClientAPI", "levelname": "WARNING", "fl_ctx": "", "message": "ask to stop job: reason: END_RUN received"}
{"asctime": "2025-10-08 19:29:24,070", "name": "InProcessClientAPI", "fullName": "nvflare.client.in_process.api.InProcessClientAPI", "levelname": "WARNING", "fl_ctx": "", "message": "request to stop the job for reason END_RUN received"}
{"asctime": "2025-10-08 19:29:24,071", "name": "ClientRunner", "fullName": "nvflare.private.fed.client.client_runner.ClientRunner", "levelname": "INFO", "fl_ctx": "[identity=site-2, run=simulate_job]", "message": "END_RUN fired"}
{"asctime": "2025-10-08 19:29:24,071", "name": "ClientTaskWorker", "fullName": "__main__.ClientTaskWorker", "levelname": "INFO", "fl_ctx": "", "message": "End the Simulator run."}
